hello_catalin_packages/__init__.py
hello_catalin_packages/hello.py
hello_catalin_package-0.1.0.dist-info/METADATA
hello_catalin_package-0.1.0.dist-info/WHEEL
hello_catalin_package-0.1.0.dist-info/top_level.txt
hello_catalin_package-0.1.0.dist-info/RECORD
