Metadata-Version: 2.1
Name: hello-catalin-package
Version: 0.1.0
Summary: first_package
Home-page: UNKNOWN
Author: Catalin
Author-email: anghelcatalin22@yahoo.com
License: UNKNOWN
Platform: UNKNOWN
